<?xml version="1.0" encoding="UTF-8"?>
<metadata xml:lang="en"><Esri><CreaDate>20250528</CreaDate><CreaTime>08450800</CreaTime><ArcGISFormat>1.0</ArcGISFormat><SyncOnce>TRUE</SyncOnce><DataProperties><lineage><Process ToolSource="c:\program files\arcgis\server\framework\runtime\arcgis\Resources\ArcToolbox\toolboxes\Data Management Tools.tbx\SetRasterProperties" Date="20250528" Time="084508">SetRasterProperties C:\Users\igskmncn-swscArc\AppData\Local\Temp\landfireproductservice_gpserver\j09d2f8ef002d40c9b081769966194e6c\scratch\j09d2f8ef002d40c9b081769966194e6c.tif Thematic # # # "Creator 'USGS EROS Landfire Product Service'" #</Process></lineage></DataProperties></Esri></metadata>
